MANIFEST.in
setup.py
attune/__init__.py
attune/client/__init__.py
attune/client/client.py
attune/client/commands.py
attune/client/configuration.py
attune/client/rest.py
attune/client/api/__init__.py
attune/client/api/entities.py
attune/client/model/__init__.py
attune/client/model/anonymous_result.py
attune/client/model/batch_ranking_request.py
attune/client/model/batch_ranking_result.py
attune/client/model/blacklist.py
attune/client/model/blacklist_delete_response.py
attune/client/model/blacklist_get_response.py
attune/client/model/blacklist_params.py
attune/client/model/blacklist_save_response.py
attune/client/model/blacklist_update_response.py
attune/client/model/customer.py
attune/client/model/ranked_entities.py
attune/client/model/ranking_params.py
attune/client/model/scope_entry.py
attune/client/model/void.py
attune_python.egg-info/PKG-INFO
attune_python.egg-info/SOURCES.txt
attune_python.egg-info/dependency_links.txt
attune_python.egg-info/requires.txt
attune_python.egg-info/top_level.txt