Metadata-Version: 1.0
Name: attune-python
Version: 1.0.4
Summary: Attune.co API Client
Home-page: https://github.com/attune-api/attune-python
Author: Attune.co
Author-email: python@attune.co
License: UNKNOWN
Keywords: Attune API
Platform: UNKNOWN
